ezstdf/StdfReader.py
ezstdf/StdfReaderBase.py
ezstdf/__init__.py
ezstdf/atdf_cst.py
ezstdf/parsers.py
ezstdf/stdf_cst.py
ezsdtf-0.0.1.dist-info/LICENSE
ezsdtf-0.0.1.dist-info/METADATA
ezsdtf-0.0.1.dist-info/WHEEL
ezsdtf-0.0.1.dist-info/top_level.txt
ezsdtf-0.0.1.dist-info/RECORD
