Metadata-Version: 2.1
Name: ezsdtf
Version: 0.0.1
Summary: An easy to use and fast parser for STDF files in python.
Author-email: Fabio Verna <bogies.0.revue@icloud.com>
Project-URL: Homepage, https://github.com/pypa/sampleproject
Project-URL: Bug Tracker, https://github.com/pypa/sampleproject/issues
Classifier: Programming Language :: Python :: 3
Classifier: License :: OSI Approved :: MIT License
Classifier: Operating System :: OS Independent
Requires-Python: >=3.7
License-File: LICENSE
Requires-Dist: pandas
